finta/__init__.py
finta/finta.py
finta/utils.py
finta-1.3.dist-info/LICENSE
finta-1.3.dist-info/METADATA
finta-1.3.dist-info/WHEEL
finta-1.3.dist-info/top_level.txt
finta-1.3.dist-info/RECORD
