Metadata-Version: 2.1
Name: finta
Version: 1.3
Summary:  Common financial technical indicators implemented in Pandas.
Home-page: https://github.com/peerchemist/finta
Author: Peerchemist
Author-email: peerchemist@protonmail.ch
License: LGPLv3+
Keywords: technical analysis,ta,pandas,finance,numpy,analysis
Platform: UNKNOWN
